[
  {
    "name": "saksafon",
    "price": 100,
    "imgUrl": "https://images.pexels.com/photos/164936/pexels-photo-164936.jpeg?auto=compress&cs=tinysrgb&w=600",
    "id": 10,
    "color": "gold"
  },
  {
    "name": "micro-f",
    "price": 101,
    "imgUrl": "https://images.pexels.com/photos/3783471/pexels-photo-3783471.jpeg?auto=compress&cs=tinysrgb&w=1260&h=750&dpr=1",
    "id": 11,
    "color": "silver"
  },
  {
    "name": "amplifier",
    "price": 102,
    "imgUrl": "https://images.pexels.com/photos/3784566/pexels-photo-3784566.jpeg?auto=compress&cs=tinysrgb&w=600",
    "id": 12,
    "color": "black"
  },
  {
    "name": "cassette",
    "price": 103,
    "imgUrl": "https://images.pexels.com/photos/3810824/pexels-photo-3810824.jpeg?auto=compress&cs=tinysrgb&w=1260&h=750&dpr=1",
    "id": 13,
    "color": "grey"
  },
  {
    "name": "drum",
    "price": 104,
    "imgUrl": "https://images.pexels.com/photos/1010519/pexels-photo-1010519.jpeg?auto=compress&cs=tinysrgb&w=600",
    "id": 14,
    "color": "grey"
  },
  {
    "name": "giutar",
    "price": 105,
    "imgUrl": "https://images.pexels.com/photos/995301/pexels-photo-995301.jpeg?auto=compress&cs=tinysrgb&w=600",
    "id": 15,
    "color": "silver"
  },
  {
    "name": "violin",
    "price": 106,
    "imgUrl": "https://images.pexels.com/photos/34221/violin-musical-instrument-music-sound.jpg?auto=compress&cs=tinysrgb&w=600",
    "id": 16,
    "color": "brown"
  },
  {
    "name": "piano",
    "price": 107,
    "imgUrl": "https://images.pexels.com/photos/191240/pexels-photo-191240.jpeg?auto=compress&cs=tinysrgb&w=600",
    "id": 17,
    "color": "black"
  },
  {
    "name": "violin",
    "price": 108,
    "imgUrl": "https://images.pexels.com/photos/668295/pexels-photo-668295.jpeg?auto=compress&cs=tinysrgb&w=600",
    "id": 18,
    "color": "brown"
  },
  {
    "name": "trumpet",
    "price": 109,
    "imgUrl": "https://images.pexels.com/photos/18748675/pexels-photo-18748675.jpeg?auto=compress&cs=tinysrgb&w=600",
    "id": 19,
    "color": "brown"
  }
]
